iMate/__init__.py
iMate/utils.py
iMate/web.py
Stanbic_iMate-0.0.2.dist-info/LICENSE
Stanbic_iMate-0.0.2.dist-info/METADATA
Stanbic_iMate-0.0.2.dist-info/WHEEL
Stanbic_iMate-0.0.2.dist-info/top_level.txt
Stanbic_iMate-0.0.2.dist-info/RECORD
