Metadata-Version: 2.1
Name: Stanbic-iMate
Version: 0.0.2
Summary: Intelligent Automation Library
Home-page: https://github.com/redkad/iMate
Author: Collins M. Tenge
Author-email: collinstenge@gmail.com
License: UNKNOWN
Platform: UNKNOWN
Classifier: Programming Language :: Python :: 3
Classifier: License :: OSI Approved :: MIT License
Classifier: Operating System :: OS Independent
Requires-Python: >=3.6
License-File: LICENSE
